memmachine/__init__.py
memmachine/common/__init__.py
memmachine/common/data_types.py
memmachine/common/errors.py
memmachine/common/rw_locks.py
memmachine/common/utils.py
memmachine/common/api/__init__.py
memmachine/common/api/doc.py
memmachine/common/api/spec.py
memmachine/common/api/version.py
memmachine/common/configuration/__init__.py
memmachine/common/configuration/database_conf.py
memmachine/common/configuration/default_episode_summary_system_prompt.txt
memmachine/common/configuration/default_episode_summary_user_prompt.txt
memmachine/common/configuration/embedder_conf.py
memmachine/common/configuration/episodic_config.py
memmachine/common/configuration/language_model_conf.py
memmachine/common/configuration/log_conf.py
memmachine/common/configuration/mixin_confs.py
memmachine/common/configuration/reranker_conf.py
memmachine/common/embedder/__init__.py
memmachine/common/embedder/amazon_bedrock_embedder.py
memmachine/common/embedder/embedder.py
memmachine/common/embedder/openai_embedder.py
memmachine/common/embedder/sentence_transformer_embedder.py
memmachine/common/episode_store/__init__.py
memmachine/common/episode_store/count_caching_episode_storage.py
memmachine/common/episode_store/episode_model.py
memmachine/common/episode_store/episode_sqlalchemy_store.py
memmachine/common/episode_store/episode_storage.py
memmachine/common/filter/__init__.py
memmachine/common/filter/filter_parser.py
memmachine/common/filter/sql_filter_util.py
memmachine/common/language_model/__init__.py
memmachine/common/language_model/amazon_bedrock_language_model.py
memmachine/common/language_model/language_model.py
memmachine/common/language_model/openai_chat_completions_language_model.py
memmachine/common/language_model/openai_responses_language_model.py
memmachine/common/metrics_factory/__init__.py
memmachine/common/metrics_factory/metrics_factory.py
memmachine/common/metrics_factory/prometheus_metrics_factory.py
memmachine/common/reranker/__init__.py
memmachine_client-0.2.5.dist-info/licenses/LICENSE
memmachine_client-0.2.5.dist-info/METADATA
memmachine_client-0.2.5.dist-info/WHEEL
memmachine_client-0.2.5.dist-info/top_level.txt
memmachine_client-0.2.5.dist-info/RECORD
