Metadata-Version: 2.4
Name: memmachine-client
Version: 0.2.5
Summary: MemMachine REST Client - A lightweight Python client library for MemMachine memory system
Author-email: MemMachine <noreply@memmachine.ai>
License-Expression: Apache-2.0
Project-URL: Homepage, https://github.com/MemMachine/MemMachine
Project-URL: Issues, https://github.com/MemMachine/MemMachine/issues
Keywords: memmachine,client,memory,ai,agent
Classifier: Programming Language :: Python :: 3
Classifier: Programming Language :: Python :: 3.10
Classifier: Programming Language :: Python :: 3.11
Classifier: Programming Language :: Python :: 3.12
Classifier: Programming Language :: Python :: 3.13
Classifier: Programming Language :: Python :: 3.14
Classifier: Operating System :: OS Independent
Requires-Python: >=3.10
License-File: LICENSE
Requires-Dist: pydantic>=2.0.0
Requires-Dist: regex>=2023.0.0
Requires-Dist: requests>=2.31.0
Requires-Dist: typing-extensions>=4.0.0
Requires-Dist: urllib3>=2.6.3
Dynamic: license-file
